setup.py
am43/__init__.py
am43/blind.py
am43/search.py
am43.egg-info/PKG-INFO
am43.egg-info/SOURCES.txt
am43.egg-info/dependency_links.txt
am43.egg-info/requires.txt
am43.egg-info/top_level.txt